setup.cfg
setup.py
mgPython/__init__.py
mgPython.egg-info/PKG-INFO
mgPython.egg-info/SOURCES.txt
mgPython.egg-info/dependency_links.txt
mgPython.egg-info/not-zip-safe
mgPython.egg-info/top_level.txt