Metadata-Version: 1.1
Name: mgPython
Version: 0.1
Summary: Python wrapper for Minergate API
Home-page: http://github.com/amahlaka/Minergate-python
Author: Arttu Mahlakaarto
Author-email: Arttu.mahlakaarto@gmail.com
License: UNKNOWN
Download-URL: https://github.com/amahlaka/mgPython/tarball/0.1
Platform: UNKNOWN
Classifier: Development Status :: 4 - Beta
Classifier: Intended Audience :: Developers
Classifier: License :: OSI Approved :: MIT License
Classifier: Operating System :: OS Independent
Classifier: Programming Language :: Python
